anthropic/__init__.py
anthropic/_base_client.py
anthropic/_client.py
anthropic/_compat.py
anthropic/_constants.py
anthropic/_exceptions.py
anthropic/_files.py
anthropic/_legacy_response.py
anthropic/_models.py
anthropic/_qs.py
anthropic/_resource.py
anthropic/_response.py
anthropic/_streaming.py
anthropic/_types.py
anthropic/_version.py
anthropic/pagination.py
anthropic/py.typed
anthropic/_decoders/jsonl.py
anthropic/_utils/__init__.py
anthropic/_utils/_logs.py
anthropic/_utils/_proxy.py
anthropic/_utils/_reflection.py
anthropic/_utils/_streams.py
anthropic/_utils/_sync.py
anthropic/_utils/_transform.py
anthropic/_utils/_typing.py
anthropic/_utils/_utils.py
anthropic/lib/__init__.py
anthropic/lib/_extras/__init__.py
anthropic/lib/_extras/_common.py
anthropic/lib/_extras/_google_auth.py
anthropic/lib/bedrock/__init__.py
anthropic/lib/bedrock/_auth.py
anthropic/lib/bedrock/_beta.py
anthropic/lib/bedrock/_beta_messages.py
anthropic/lib/bedrock/_client.py
anthropic/lib/bedrock/_stream.py
anthropic/lib/bedrock/_stream_decoder.py
anthropic/lib/streaming/__init__.py
anthropic/lib/streaming/_beta_messages.py
anthropic/lib/streaming/_beta_types.py
anthropic/lib/streaming/_messages.py
anthropic/lib/streaming/_types.py
anthropic/lib/vertex/__init__.py
anthropic/lib/vertex/_auth.py
anthropic/lib/vertex/_beta.py
anthropic/lib/vertex/_beta_messages.py
anthropic/lib/vertex/_client.py
anthropic/resources/__init__.py
anthropic/resources/completions.py
anthropic/resources/models.py
anthropic/resources/beta/__init__.py
anthropic/resources/beta/beta.py
anthropic/resources/beta/models.py
anthropic/resources/beta/messages/__init__.py
anthropic/resources/beta/messages/batches.py
anthropic/resources/beta/messages/messages.py
anthropic/resources/messages/__init__.py
anthropic/resources/messages/batches.py
anthropic/resources/messages/messages.py
anthropic/types/__init__.py
anthropic/types/anthropic_beta_param.py
anthropic/types/base64_image_source_param.py
anthropic_aipy-0.49.0.2.dist-info/METADATA
anthropic_aipy-0.49.0.2.dist-info/WHEEL
anthropic_aipy-0.49.0.2.dist-info/top_level.txt
anthropic_aipy-0.49.0.2.dist-info/RECORD
